<?xml version="1.0" encoding="utf-8"?>
<cms.webpageurlpath>
  <WebPageUrlPath>es/Recipes/Hour-Glass-Frittata/Spinach-Cheese</WebPageUrlPath>
  <WebPageUrlPathContentLanguageID>
    <CodeName>es</CodeName>
    <GUID>ef3c384b-a9ef-42c4-a1dc-21f748137808</GUID>
    <ObjectType>cms.contentlanguage</ObjectType>
  </WebPageUrlPathContentLanguageID>
  <WebPageUrlPathGUID>ce8f8152-e868-49ef-b516-0244a73990fa</WebPageUrlPathGUID>
  <WebPageUrlPathHash>
    <![CDATA[94E1315B7476871BAB9454CE328049C44EA002D2FC22EE1A4BF28D905CEE9BC6]]>
  </WebPageUrlPathHash>
  <WebPageUrlPathIsCanonical>True</WebPageUrlPathIsCanonical>
  <WebPageUrlPathIsDraft>False</WebPageUrlPathIsDraft>
  <WebPageUrlPathIsLatest>True</WebPageUrlPathIsLatest>
  <WebPageUrlPathType>0</WebPageUrlPathType>
  <WebPageUrlPathWebPageItemID>
    <CodeName>Spinach_Cheese-ird9sb1c</CodeName>
    <GUID>c2078f66-aeea-4605-a50c-b1262aeb4c0e</GUID>
    <ObjectType>cms.webpageitem</ObjectType>
  </WebPageUrlPathWebPageItemID>
  <WebPageUrlPathWebsiteChannelID>
    <GUID>25dd5a69-ad53-4fb6-98a3-8f6e1b53607f</GUID>
    <ObjectType>cms.websitechannel</ObjectType>
    <Parent>
      <CodeName>KCC</CodeName>
      <GUID>c5ac4825-e084-4e36-9912-b3f8387360ba</GUID>
      <ObjectType>cms.channel</ObjectType>
    </Parent>
  </WebPageUrlPathWebsiteChannelID>
</cms.webpageurlpath>