<?xml version="1.0" encoding="utf-8"?>
<cms.webpageurlpath>
  <WebPageUrlPath>es/Recipes/Legendary-Lasagna/Classic-Beef-Lasagna</WebPageUrlPath>
  <WebPageUrlPathContentLanguageID>
    <CodeName>es</CodeName>
    <GUID>ef3c384b-a9ef-42c4-a1dc-21f748137808</GUID>
    <ObjectType>cms.contentlanguage</ObjectType>
  </WebPageUrlPathContentLanguageID>
  <WebPageUrlPathGUID>f13f099e-0cf1-4d3d-a3c8-2d12c09307bc</WebPageUrlPathGUID>
  <WebPageUrlPathHash>
    <![CDATA[8126234389173300557104FA0151B78EA1023E22CCF3397CDD44F070B8AE389B]]>
  </WebPageUrlPathHash>
  <WebPageUrlPathIsCanonical>True</WebPageUrlPathIsCanonical>
  <WebPageUrlPathIsDraft>False</WebPageUrlPathIsDraft>
  <WebPageUrlPathIsLatest>True</WebPageUrlPathIsLatest>
  <WebPageUrlPathType>0</WebPageUrlPathType>
  <WebPageUrlPathWebPageItemID>
    <CodeName>ClassicBeefLasagna-2dldyvtj</CodeName>
    <GUID>ebf0d31d-54f5-4f34-8943-b5b5996cbc91</GUID>
    <ObjectType>cms.webpageitem</ObjectType>
  </WebPageUrlPathWebPageItemID>
  <WebPageUrlPathWebsiteChannelID>
    <GUID>25dd5a69-ad53-4fb6-98a3-8f6e1b53607f</GUID>
    <ObjectType>cms.websitechannel</ObjectType>
    <Parent>
      <CodeName>KCC</CodeName>
      <GUID>c5ac4825-e084-4e36-9912-b3f8387360ba</GUID>
      <ObjectType>cms.channel</ObjectType>
    </Parent>
  </WebPageUrlPathWebsiteChannelID>
</cms.webpageurlpath>